opatio/__init__.py
opatio/base/__init__.py
opatio/base/header.py
opatio/base/opat.py
opatio/card/__init__.py
opatio/card/datacard.py
opatio/catalog/__init__.py
opatio/catalog/entry.py
opatio/convert/__init__.py
opatio/convert/opal.py
opatio/index/__init__.py
opatio/index/floatvectorindex.py
opatio/lattice/__init__.py
opatio/lattice/tableLattice.py
opatio/load/__init__.py
opatio/load/load.py
opatio/misc/__init__.py
opatio/misc/misc.py
opatio/misc/opatentity.py
opatio-0.3.0.dist-info/METADATA
opatio-0.3.0.dist-info/WHEEL
opatio-0.3.0.dist-info/top_level.txt
opatio-0.3.0.dist-info/RECORD
