Metadata-Version: 2.4
Name: opatio
Version: 0.3.0
Summary: A python module for handling OPAT files
Author: 4D-STAR Collaboration
Author-email: "Emily M. Boudreaux" <emily.boudreaux@dartmouth.edu>
Maintainer-email: "Emily M. Boudreaux" <emily.boudreaux@dartmouth.edu>
Project-URL: Homepage, https://github.com/4D-STAR/opat-core/tree/main/opatIO-py
Project-URL: Documentation, https://4d-star.github.io/opat-core/
Project-URL: Issues, https://github.com/4D-STAR/opat-core/issues
Project-URL: 4D-STAR, https://4d-star.org/
Keywords: astrophysics,OPAT,opatcity
Classifier: Development Status :: 3 - Alpha
Classifier: Intended Audience :: Science/Research
Classifier: Programming Language :: Python :: 3
Classifier: Topic :: Scientific/Engineering :: Astronomy
Classifier: Operating System :: OS Independent
Requires-Python: >=3.8
Requires-Dist: numpy>=1.21.1
Requires-Dist: xxhash>=3.5.0
Requires-Dist: scipy>=1.15.0
